carbonarr/__init__.py
carbonarr/carbonarr.py
carbonarr/common.py
carbonarr/utils.py
carbonarr-0.0.9.dist-info/LICENSE
carbonarr-0.0.9.dist-info/METADATA
carbonarr-0.0.9.dist-info/WHEEL
carbonarr-0.0.9.dist-info/entry_points.txt
carbonarr-0.0.9.dist-info/top_level.txt
carbonarr-0.0.9.dist-info/RECORD
