Metadata-Version: 2.1
Name: carbonarr
Version: 0.0.9
Summary: A python package to do all ARR GIS analysis.
Author-email: Tushar Bharadwaj <ttushar684@gmail.com>
License: MIT License
Project-URL: Homepage, https://github.com/tushar684b/carbonarr
Keywords: carbonarr
Classifier: Intended Audience :: Developers
Classifier: License :: OSI Approved :: MIT License
Classifier: Natural Language :: English
Classifier: Programming Language :: Python :: 3.8
Classifier: Programming Language :: Python :: 3.9
Classifier: Programming Language :: Python :: 3.10
Classifier: Programming Language :: Python :: 3.11
Classifier: Programming Language :: Python :: 3.12
Requires-Python: >=3.8
License-File: LICENSE
Requires-Dist: numpy
Requires-Dist: ipyleaflet
Requires-Dist: shapely
Requires-Dist: geopandas
Provides-Extra: all
Requires-Dist: carbonarr[extra] ; extra == 'all'
Provides-Extra: extra
Requires-Dist: pandas ; extra == 'extra'
